{
  "@context": "http://iiif.io/api/presentation/3/context.json",
  "id": "https://kywark.github.io/link-tests/allen-ginsberg-at-sgwu-1969/canvas-1/canvas/S_Layer.json",
  "type": "AnnotationPage",
  "label": "S_Layer",
  "items": [
    {
      "@context": "http://www.w3.org/ns/anno.jsonld",
      "id": "https://kywark.github.io/link-tests/allen-ginsberg-at-sgwu-1969/canvas-1/canvas/S_Layer-annotation-0.json",
      "type": "Annotation",
      "motivation": [
        "supplementing",
        "commenting"
      ],
      "body": {
        "type": "TextualBody",
        "value": "Live Indian Band",
        "format": "text/plain"
      },
      "target": {
        "source": "https://kywark.github.io/link-tests/allen-ginsberg-at-sgwu-1969/canvas-1/canvas",
        "selector": {
          "type": "PointSelector",
          "t": "1003"
        }
      }
    },
    {
      "@context": "http://www.w3.org/ns/anno.jsonld",
      "id": "https://kywark.github.io/link-tests/allen-ginsberg-at-sgwu-1969/canvas-1/canvas/S_Layer-annotation-1.json",
      "type": "Annotation",
      "motivation": [
        "supplementing",
        "commenting"
      ],
      "body": {
        "type": "TextualBody",
        "value": "George Bowering Introduces Allen Ginsberg",
        "format": "text/plain"
      },
      "target": {
        "source": "https://kywark.github.io/link-tests/allen-ginsberg-at-sgwu-1969/canvas-1/canvas",
        "selector": {
          "type": "PointSelector",
          "t": "1003"
        }
      }
    },
    {
      "@context": "http://www.w3.org/ns/anno.jsonld",
      "id": "https://kywark.github.io/link-tests/allen-ginsberg-at-sgwu-1969/canvas-1/canvas/S_Layer-annotation-2.json",
      "type": "Annotation",
      "motivation": [
        "supplementing",
        "commenting"
      ],
      "body": {
        "type": "TextualBody",
        "value": "Allen Ginsberg Talking",
        "format": "text/plain"
      },
      "target": {
        "source": "https://kywark.github.io/link-tests/allen-ginsberg-at-sgwu-1969/canvas-1/canvas",
        "selector": {
          "type": "PointSelector",
          "t": "1104.88"
        }
      }
    },
    {
      "@context": "http://www.w3.org/ns/anno.jsonld",
      "id": "https://kywark.github.io/link-tests/allen-ginsberg-at-sgwu-1969/canvas-1/canvas/S_Layer-annotation-3.json",
      "type": "Annotation",
      "motivation": [
        "supplementing",
        "commenting"
      ],
      "body": {
        "type": "TextualBody",
        "value": "Allen Ginsberg Reads \"Angkor Wat\"",
        "format": "text/plain"
      },
      "target": {
        "source": "https://kywark.github.io/link-tests/allen-ginsberg-at-sgwu-1969/canvas-1/canvas",
        "selector": {
          "type": "PointSelector",
          "t": "1136.67"
        }
      }
    },
    {
      "@context": "http://www.w3.org/ns/anno.jsonld",
      "id": "https://kywark.github.io/link-tests/allen-ginsberg-at-sgwu-1969/canvas-1/canvas/S_Layer-annotation-4.json",
      "type": "Annotation",
      "motivation": [
        "supplementing",
        "commenting"
      ],
      "body": {
        "type": "TextualBody",
        "value": "singing in poem",
        "format": "text/plain"
      },
      "target": {
        "source": "https://kywark.github.io/link-tests/allen-ginsberg-at-sgwu-1969/canvas-1/canvas",
        "selector": {
          "type": "RangeSelector",
          "t": "1484.54,1489.12"
        }
      }
    },
    {
      "@context": "http://www.w3.org/ns/anno.jsonld",
      "id": "https://kywark.github.io/link-tests/allen-ginsberg-at-sgwu-1969/canvas-1/canvas/S_Layer-annotation-5.json",
      "type": "Annotation",
      "motivation": [
        "supplementing",
        "commenting"
      ],
      "body": {
        "type": "TextualBody",
        "value": "Allen Ginsberg Speaking",
        "format": "text/plain"
      },
      "target": {
        "source": "https://kywark.github.io/link-tests/allen-ginsberg-at-sgwu-1969/canvas-1/canvas",
        "selector": {
          "type": "PointSelector",
          "t": "2508.65"
        }
      }
    },
    {
      "@context": "http://www.w3.org/ns/anno.jsonld",
      "id": "https://kywark.github.io/link-tests/allen-ginsberg-at-sgwu-1969/canvas-1/canvas/S_Layer-annotation-6.json",
      "type": "Annotation",
      "motivation": [
        "supplementing",
        "commenting"
      ],
      "body": {
        "type": "TextualBody",
        "value": "Allen Ginsberg Reading \"Understand That This Is A Dream\"",
        "format": "text/plain"
      },
      "target": {
        "source": "https://kywark.github.io/link-tests/allen-ginsberg-at-sgwu-1969/canvas-1/canvas",
        "selector": {
          "type": "PointSelector",
          "t": "2541"
        }
      }
    },
    {
      "@context": "http://www.w3.org/ns/anno.jsonld",
      "id": "https://kywark.github.io/link-tests/allen-ginsberg-at-sgwu-1969/canvas-1/canvas/S_Layer-annotation-7.json",
      "type": "Annotation",
      "motivation": [
        "supplementing",
        "commenting"
      ],
      "body": {
        "type": "TextualBody",
        "value": "Allen Ginsberg Speaking",
        "format": "text/plain"
      },
      "target": {
        "source": "https://kywark.github.io/link-tests/allen-ginsberg-at-sgwu-1969/canvas-1/canvas",
        "selector": {
          "type": "PointSelector",
          "t": "2977.61"
        }
      }
    },
    {
      "@context": "http://www.w3.org/ns/anno.jsonld",
      "id": "https://kywark.github.io/link-tests/allen-ginsberg-at-sgwu-1969/canvas-1/canvas/S_Layer-annotation-8.json",
      "type": "Annotation",
      "motivation": [
        "supplementing",
        "commenting"
      ],
      "body": {
        "type": "TextualBody",
        "value": "Allen Ginsberg Singing \"Piping down the valleys wild\" + Live Music\"",
        "format": "text/plain"
      },
      "target": {
        "source": "https://kywark.github.io/link-tests/allen-ginsberg-at-sgwu-1969/canvas-1/canvas",
        "selector": {
          "type": "PointSelector",
          "t": "2992.01"
        }
      }
    },
    {
      "@context": "http://www.w3.org/ns/anno.jsonld",
      "id": "https://kywark.github.io/link-tests/allen-ginsberg-at-sgwu-1969/canvas-1/canvas/S_Layer-annotation-9.json",
      "type": "Annotation",
      "motivation": [
        "supplementing",
        "commenting"
      ],
      "body": {
        "type": "TextualBody",
        "value": "Allen Ginsberg Singing \"How sweet is the shepherd's sweet lot\"",
        "format": "text/plain"
      },
      "target": {
        "source": "https://kywark.github.io/link-tests/allen-ginsberg-at-sgwu-1969/canvas-1/canvas",
        "selector": {
          "type": "PointSelector",
          "t": "3081.51"
        }
      }
    },
    {
      "@context": "http://www.w3.org/ns/anno.jsonld",
      "id": "https://kywark.github.io/link-tests/allen-ginsberg-at-sgwu-1969/canvas-1/canvas/S_Layer-annotation-10.json",
      "type": "Annotation",
      "motivation": [
        "supplementing",
        "commenting"
      ],
      "body": {
        "type": "TextualBody",
        "value": "Allen Ginsberg Speaking",
        "format": "text/plain"
      },
      "target": {
        "source": "https://kywark.github.io/link-tests/allen-ginsberg-at-sgwu-1969/canvas-1/canvas",
        "selector": {
          "type": "PointSelector",
          "t": "3151.36"
        }
      }
    },
    {
      "@context": "http://www.w3.org/ns/anno.jsonld",
      "id": "https://kywark.github.io/link-tests/allen-ginsberg-at-sgwu-1969/canvas-1/canvas/S_Layer-annotation-11.json",
      "type": "Annotation",
      "motivation": [
        "supplementing",
        "commenting"
      ],
      "body": {
        "type": "TextualBody",
        "value": "Allen Ginsberg Singing \"The Echoing Green\"",
        "format": "text/plain"
      },
      "target": {
        "source": "https://kywark.github.io/link-tests/allen-ginsberg-at-sgwu-1969/canvas-1/canvas",
        "selector": {
          "type": "PointSelector",
          "t": "3160.61"
        }
      }
    },
    {
      "@context": "http://www.w3.org/ns/anno.jsonld",
      "id": "https://kywark.github.io/link-tests/allen-ginsberg-at-sgwu-1969/canvas-1/canvas/S_Layer-annotation-12.json",
      "type": "Annotation",
      "motivation": [
        "supplementing",
        "commenting"
      ],
      "body": {
        "type": "TextualBody",
        "value": "Allen Ginsberg Singing \"The Little Boy Lost\" and \"The Little Boy Found\"",
        "format": "text/plain"
      },
      "target": {
        "source": "https://kywark.github.io/link-tests/allen-ginsberg-at-sgwu-1969/canvas-1/canvas",
        "selector": {
          "type": "PointSelector",
          "t": "3283"
        }
      }
    },
    {
      "@context": "http://www.w3.org/ns/anno.jsonld",
      "id": "https://kywark.github.io/link-tests/allen-ginsberg-at-sgwu-1969/canvas-1/canvas/S_Layer-annotation-13.json",
      "type": "Annotation",
      "motivation": [
        "supplementing",
        "commenting"
      ],
      "body": {
        "type": "TextualBody",
        "value": "Allen Ginsberg Singing \"The Blossom\"",
        "format": "text/plain"
      },
      "target": {
        "source": "https://kywark.github.io/link-tests/allen-ginsberg-at-sgwu-1969/canvas-1/canvas",
        "selector": {
          "type": "PointSelector",
          "t": "3375"
        }
      }
    },
    {
      "@context": "http://www.w3.org/ns/anno.jsonld",
      "id": "https://kywark.github.io/link-tests/allen-ginsberg-at-sgwu-1969/canvas-1/canvas/S_Layer-annotation-14.json",
      "type": "Annotation",
      "motivation": [
        "supplementing",
        "commenting"
      ],
      "body": {
        "type": "TextualBody",
        "value": "Allen Ginsberg Singing \"Hear the Voice of the Bard\"",
        "format": "text/plain"
      },
      "target": {
        "source": "https://kywark.github.io/link-tests/allen-ginsberg-at-sgwu-1969/canvas-1/canvas",
        "selector": {
          "type": "PointSelector",
          "t": "3445"
        }
      }
    },
    {
      "@context": "http://www.w3.org/ns/anno.jsonld",
      "id": "https://kywark.github.io/link-tests/allen-ginsberg-at-sgwu-1969/canvas-1/canvas/S_Layer-annotation-15.json",
      "type": "Annotation",
      "motivation": [
        "supplementing",
        "commenting"
      ],
      "body": {
        "type": "TextualBody",
        "value": "Allen Ginsberg Singing \"Youth of Delight, Come Hither\"",
        "format": "text/plain"
      },
      "target": {
        "source": "https://kywark.github.io/link-tests/allen-ginsberg-at-sgwu-1969/canvas-1/canvas",
        "selector": {
          "type": "PointSelector",
          "t": "3571"
        }
      }
    },
    {
      "@context": "http://www.w3.org/ns/anno.jsonld",
      "id": "https://kywark.github.io/link-tests/allen-ginsberg-at-sgwu-1969/canvas-1/canvas/S_Layer-annotation-16.json",
      "type": "Annotation",
      "motivation": [
        "supplementing",
        "commenting"
      ],
      "body": {
        "type": "TextualBody",
        "value": "Allen Ginsberg Singing \"The Laughing Song\"",
        "format": "text/plain"
      },
      "target": {
        "source": "https://kywark.github.io/link-tests/allen-ginsberg-at-sgwu-1969/canvas-1/canvas",
        "selector": {
          "type": "PointSelector",
          "t": "3648"
        }
      }
    }
  ]
}